filecompare/__init__.py
filecompare/__main__.py
filecompare/funcmodule.py
filecompare-0.1.5.dist-info/LICENSE
filecompare-0.1.5.dist-info/METADATA
filecompare-0.1.5.dist-info/WHEEL
filecompare-0.1.5.dist-info/entry_points.txt
filecompare-0.1.5.dist-info/top_level.txt
filecompare-0.1.5.dist-info/RECORD
